{
    "status": "ok",
    "totalResults": 47494,
    "articles": [
        {
            "source": {
                "id": "wired",
                "name": "Wired"
            },
            "author": "Elana Klein",
            "title": "Dating Apps Are Using Roleplaying Games to Fix Your Rizz",
            "description": "Tinder, Hinge, Bumble, and Grindr are rolling out scenario-based training, AI, and other tools to address their users’ lack of romantic experience.",
            "url": "https://www.wired.com/story/dating-apps-are-using-roleplaying-games-to-fix-your-rizz/",
            "urlToImage": "https://media.wired.com/photos/68015da678b3d00206ec7aa6/191:100/w_1280,c_limit/Dating-Apps-Teaching-Rizz-1631581349.jpg",
            "publishedAt": "2025-04-30T21:14:40Z",
            "content": "Im given the following scenario: Im at a friends housewarming party and accidentally break a vase that turns out was a gift for the host brought by 35-year-old Caleb, a financial analyst from Annapol… [+2789 chars]"
        },
        {
            "source": {
                "id": "wired",
                "name": "Wired"
            },
            "author": "Megan Farokhmanesh",
            "title": "So You’ve Got a 'Fortnite' Accent and You Want to Get Rid of It",
            "description": "Players of the mega-popular battle royale game have a particular way of speaking. Unlearning it can be a challenge.",
            "url": "https://www.wired.com/story/so-youve-got-a-fortnite-accent-and-you-want-to-get-rid-of-it/",
            "urlToImage": "https://media.wired.com/photos/67f6a10cbb508ba698b749c2/191:100/w_1280,c_limit/Fortnite-Accent-Culture-1832710593.jpg",
            "publishedAt": "2025-04-09T18:20:43Z",
            "content": "Everyone has an accent. Typically, its a marker for where someone grew up, or in some celebrity cases, a bored rich person trying on a new persona. But did you know Fortnite players have their own ac… [+2041 chars]"
        },
        {
            "source": {
                "id": "wired",
                "name": "Wired"
            },
            "author": "Adrienne So",
            "title": "Aviron Victory Treadmill Review: Get Low",
            "description": "Entry-level exercisers will love Aviron’s low profile and tons of addicting exercise content.",
            "url": "https://www.wired.com/review/aviron-victory-treadmill/",
            "urlToImage": "https://media.wired.com/photos/680abfb30701665ad02c7fec/191:100/w_1280,c_limit/Aviron-Victory-Treadmill_042024_Lede.jpg",
            "publishedAt": "2025-04-25T13:00:00Z",
            "content": "My daughter recently asked me what these white flecks were on the Aviron Victory Treadmill in her playroom. Dried oobleck, I told hera corn starch slurry mixed with water. One of the neighborhood kid… [+1799 chars]"
        },
        {
            "source": {
                "id": "wired",
                "name": "Wired"
            },
            "author": "Paresh Dave",
            "title": "Apple May Face Criminal Charges for Allegedly Lying to a Federal Judge",
            "description": "A US judge says Apple deliberately chose not to comply with an order requiring it to loosen App Store rules—and then tried to cover up its disobedience.",
            "url": "https://www.wired.com/story/antitrust-judge-asks-doj-prosecute-apple/",
            "urlToImage": "https://media.wired.com/photos/6812b2ad2fb47b18ddd52359/191:100/w_1280,c_limit/Apple-Antitrust-Judge-Business-2194365320.jpg",
            "publishedAt": "2025-05-01T00:20:26Z",
            "content": "Apple willfully chose not to comply with a court order to loosen its app store restrictionsand one of its executives lied under oath about the companys plans, a federal judge wrote on Wednesday.\r\nJud… [+2982 chars]"
        },
        {
            "source": {
                "id": "wired",
                "name": "Wired"
            },
            "author": "Angela Watercutter",
            "title": "What ‘The Last of Us’ Season Premiere’s Final Moments Really Mean",
            "description": "During the second-season premiere of “The Last of Us,” Ellie gets called a homophobic slur. Craig Mazin tells WIRED it highlights what happens when humanity stops moving forward.",
            "url": "https://www.wired.com/story/last-of-us-season-2-premiere/",
            "urlToImage": "https://media.wired.com/photos/67eb0ab0eb7daf243ebce661/191:100/w_1280,c_limit/Last-Of-Us-Queer-Lives-Culture-isabela-merced-bella-ramsey_0.jpg",
            "publishedAt": "2025-04-14T02:00:00Z",
            "content": "These tensions emerge in season 2 in Jackson, Wyoming, where dozens of survivors of the Cordyceps plague have built a somewhat safe and stable existence. Joels brother Tommy (Gabriel Luna) and his wi… [+3036 chars]"
        },
        {
            "source": {
                "id": "wired",
                "name": "Wired"
            },
            "author": "Ben Dowsett",
            "title": "This Massive Screen for Live Sports Puts You in the Best Seat in the Stadium",
            "description": "Cosm's cushy venues provide a fully immersive experience that helps sports fans feel like they're really at the game—with all the thrills, the shouting, and even the hot dogs.",
            "url": "https://www.wired.com/story/cosm-live-sports-immersive-experiences/",
            "urlToImage": "https://media.wired.com/photos/67fe724b033cbe21c61cf0cd/191:100/w_1280,c_limit/TX%20V.%20MI.jpg",
            "publishedAt": "2025-04-21T10:00:00Z",
            "content": "On the sports side, both the NBA (Cosms first league partner) and NHL experiences are amazing. Cosm can put you courtside for NBA games, both at center court and on either baseline. The NHL program f… [+2416 chars]"
        },
        {
            "source": {
                "id": "wired",
                "name": "Wired"
            },
            "author": "Luke Larsen",
            "title": "Asus Vivobook Pro 15 Review: For Creators and Gamers",
            "description": "Asus’ 15-inch laptop is an uninspiring machine built for creators.",
            "url": "https://www.wired.com/review/asus-vivobook-pro-15-2025/",
            "urlToImage": "https://media.wired.com/photos/68100b10b3fb52fe96b6ff19/191:100/w_1280,c_limit/Asus-Vivobook-Pro-15_042025_Lede.jpg",
            "publishedAt": "2025-04-29T12:30:00Z",
            "content": "A discrete GPU means the Vivobook Pro 15 offers some solid gaming performance, even if thats not the main purpose of this laptop. I tested a few games, such as Cyberpunk 2077 and Marvel Rivals. Becau… [+2124 chars]"
        },
        {
            "source": {
                "id": "wired",
                "name": "Wired"
            },
            "author": "Julian Chokkattu",
            "title": "Google Pixel 9a Review: Still the Best Smartphone",
            "description": "It might not look like a classic Pixel phone anymore, but this Android is still the best smartphone bargain.",
            "url": "https://www.wired.com/review/google-pixel-9a/",
            "urlToImage": "https://media.wired.com/photos/67f718945c48f9cdda473588/191:100/w_1280,c_limit/Google's-Pixel-9a_042025_Lede.jpg",
            "publishedAt": "2025-04-10T13:00:00Z",
            "content": "Google is employing the same top-end Tensor G4 processor as the Pixel 9 series, though you get only 8 gigabytes of RAM versus 12 on the Pixel 9 and 16 on the Pixel 9 Pro. For the most part, performan… [+2862 chars]"
        },
        {
            "source": {
                "id": "wired",
                "name": "Wired"
            },
            "author": "Matt Burgess, Lily Hay Newman, Dhruv Mehrotra",
            "title": "Hacking Spree Hits UK Retail Giants",
            "description": "Plus: France blames Russia for a series of cyberattacks, the US is taking steps to crack down on a gray market allegedly used by scammers, and Microsoft pushes the password one step closer to death.",
            "url": "https://www.wired.com/story/hacking-spree-hits-uk-retail-giants/",
            "urlToImage": "",
            "publishedAt": "2025-05-03T10:30:00Z",
            "content": "Over the past two years, Scattered Spider has emerged as one of the most prolific and dangerous sets of hackers currently operating. The threat actors are not a well-defined group of hackers. Instead… [+3191 chars]"
        },
        {
            "source": {
                "id": "the-verge",
                "name": "The Verge"
            },
            "author": "Jay Peters",
            "title": "Steve Jackson Games says tariffs are a ‘seismic shift’ for board games",
            "description": "The CEO of Steve Jackson Games, which makes board games and card games, says that the 54 percent tariff on goods imported from China that will go into effect on April 5th is a “seismic shift” for the board game industry and that “prices are going up.” “At Ste…",
            "url": "https://www.theverge.com/news/643173/trump-tariffs-steve-jackson-board-game-industry",
            "urlToImage": "https://platform.theverge.com/wp-content/uploads/sites/2/2025/04/STKS488_TARIFFS_3_CVirginia_A.jpg?quality=90&strip=all&crop=0%2C10.732984293194%2C100%2C78.534031413613&w=1200",
            "publishedAt": "2025-04-03T23:56:34Z",
            "content": "The companys CEO says that Trumps tariff on China means that prices are going up.\r\nThe companys CEO says that Trumps tariff on China means that prices are going up.\r\nThe CEO of Steve Jackson Games, w… [+2244 chars]"
        },
        {
            "source": {
                "id": "the-verge",
                "name": "The Verge"
            },
            "author": "Jay Peters",
            "title": "A judge just blew up Apple’s control of the App Store",
            "description": "Epic Games v. Apple judge Yvonne Gonzalez Rogers just ruled that, effective immediately, Apple is no longer allowed to collect fees on purchases made outside apps and blocks the company from restricting how developers can point users to where they can make pu…",
            "url": "https://www.theverge.com/news/659246/apple-epic-app-store-judge-ruling-control",
            "urlToImage": "https://platform.theverge.com/wp-content/uploads/sites/2/2025/04/STK468_APPLE_ANTITRUST_CVIRGINIA_F.jpg?quality=90&strip=all&crop=0%2C10.732984293194%2C100%2C78.534031413613&w=1200",
            "publishedAt": "2025-04-30T23:04:27Z",
            "content": "The judge in Epic v. Apple has banned Apple from charging a commission on purchases made outside the App Store because of its ongoing anticompetitive behavior.\r\nThe judge in Epic v. Apple has banned … [+1136 chars]"
        },
        {
            "source": {
                "id": "the-verge",
                "name": "The Verge"
            },
            "author": "Todd Haselton",
            "title": "WD’s 2TB SSD for Xbox is $50 off and the M4 MacBook Air is just $899",
            "description": "Maybe, like me, you bought the Xbox Series S with 512GB of storage and realized, after installing Call of Duty: Black Ops 6, that you don’t have much (or any) space left for any other games. And maybe, like me, you had to hunt for another drive so you could i…",
            "url": "https://www.theverge.com/tech/656169/wd-black-c50-xbox-storage-card-m4-macbook-air-deal-sale",
            "urlToImage": "https://platform.theverge.com/wp-content/uploads/sites/2/chorus/uploads/chorus_asset/file/25739519/wd_black_c50.jpg?quality=90&strip=all&crop=0%2C10.732984293194%2C100%2C78.534031413613&w=1200",
            "publishedAt": "2025-04-25T17:11:46Z",
            "content": "Now you can store more than just Call of Duty: Black Ops 6 on your Xbox Series S.\r\nNow you can store more than just Call of Duty: Black Ops 6 on your Xbox Series S.\r\nMaybe, like me, you bought the Xb… [+2055 chars]"
        },
        {
            "source": {
                "id": "the-verge",
                "name": "The Verge"
            },
            "author": "Ash Parrish",
            "title": "Nintendo’s Switch 2 upgrade packs for Zelda will cost $9.99",
            "description": "Nintendo’s hoping to relieve some of the sticker shock it gave fans with its game pricing with the news that the Switch 2 upgrades for both Legend of Zelda games will only cost $10 if you already own them. The games are priced for the Nintendo Switch 2 at $69…",
            "url": "https://www.theverge.com/news/644516/legend-of-zelda-switch-2-upgrade-price",
            "urlToImage": "https://platform.theverge.com/wp-content/uploads/sites/2/chorus/uploads/chorus_asset/file/25362335/Switch_SequelZeldaBOTW_screen_01__1_.png?quality=90&strip=all&crop=0%2C3.4613147178592%2C100%2C93.077370564282&w=1200",
            "publishedAt": "2025-04-07T16:13:07Z",
            "content": "You can get Breath of the Wild and Tears of the Kingdom on the Switch 2 for cheap but only if you already own them.\r\nYou can get Breath of the Wild and Tears of the Kingdom on the Switch 2 for cheap … [+1724 chars]"
        },
        {
            "source": {
                "id": "the-verge",
                "name": "The Verge"
            },
            "author": "Jay Peters",
            "title": "Netflix is getting a Peppa Pig mobile game",
            "description": "Netflix is adding a Peppa Pig game to its roster of available titles for subscribers in June, the company announced on Monday. World of Peppa Pig will be available alongside new episodes of the popular children’s show in the US. “From spot the difference and …",
            "url": "https://www.theverge.com/news/644019/netflix-peppa-pig-game",
            "urlToImage": "https://platform.theverge.com/wp-content/uploads/sites/2/2025/04/unnamed.png?quality=90&strip=all&crop=0%2C3.4613147178592%2C100%2C93.077370564282&w=1200",
            "publishedAt": "2025-04-07T12:11:30Z",
            "content": "The game will join Netflixs roster in June.\r\nThe game will join Netflixs roster in June.\r\nNetflix is adding a Peppa Pig game to its roster of available titles for subscribers in June, the company ann… [+804 chars]"
        },
        {
            "source": {
                "id": "the-verge",
                "name": "The Verge"
            },
            "author": "Antonio G. Di Benedetto",
            "title": "FromSoftware’s Miyazaki assures fans the studio will still make single-player games",
            "description": "In a multi-part interview with Nintendo about newly-announced Switch 2 exclusive The Duskbloods, director Hidetaka Miyazaki tried to dispel worries that developer FromSoftware is shifting focus away from single-player games. The studio known for single-player…",
            "url": "https://www.theverge.com/news/643368/duskbloods-details-nintendo-switch-2-miyazaki-interview-fromsoftware-single-player-multiplayer",
            "urlToImage": "https://platform.theverge.com/wp-content/uploads/sites/2/2025/04/the-duskbloods-screenshot.png?quality=90&strip=all&crop=0%2C3.3223932692558%2C100%2C93.355213461488&w=1200",
            "publishedAt": "2025-04-04T16:27:30Z",
            "content": "In a Nintendo blog interview, the famed game director also shared new details about The Duskbloods.\r\nIn a Nintendo blog interview, the famed game director also shared new details about The Duskbloods… [+3385 chars]"
        },
        {
            "source": {
                "id": "the-verge",
                "name": "The Verge"
            },
            "author": "Jay Peters",
            "title": "‘Video games are not manufactured in China,’ Playasia reassures tariff-wary customers",
            "description": "Playasia, a popular retailer for buying video games, toys, and more from Asia, says that it “does not expect” the Trump administration’s planned import rule changes on Chinese-made goods to apply to “game-related orders” because “those orders will not include…",
            "url": "https://www.theverge.com/news/657560/playasia-video-games-manufactured-china",
            "urlToImage": "https://platform.theverge.com/wp-content/uploads/sites/2/2025/01/STKS488_TARIFFS_CVirginia_A.jpg?quality=90&strip=all&crop=0%2C10.732984293194%2C100%2C78.534031413613&w=1200",
            "publishedAt": "2025-04-28T22:05:51Z",
            "content": "The company says that video games are currently primarily manufactured in Japan.\r\nThe company says that video games are currently primarily manufactured in Japan.\r\nPlayasia, a popular retailer for bu… [+1169 chars]"
        },
        {
            "source": {
                "id": "the-verge",
                "name": "The Verge"
            },
            "author": "Andrew Webster",
            "title": "Sony is now selling both Last of Us games in one package",
            "description": "Just ahead of the second season of The Last of Us on HBO, Sony is making it a little easier for newcomers to get the full game experience. The company just announced The Last of Us Complete for the PS5, which is exactly what it sounds like: a collection featu…",
            "url": "https://www.theverge.com/news/646661/the-last-of-us-complete-ps5-collection-date-trailer",
            "urlToImage": "https://platform.theverge.com/wp-content/uploads/sites/2/chorus/uploads/chorus_asset/file/25221634/thumbnail_2000px_4.jpg?quality=90&strip=all&crop=0%2C3.4613147178592%2C100%2C93.077370564282&w=1200",
            "publishedAt": "2025-04-10T17:32:41Z",
            "content": "Just ahead of the second season of The Last of Us on HBO, Sony is making it a little easier for newcomers to get the full game experience. The company just announced The Last of Us Complete for the P… [+825 chars]"
        },
        {
            "source": {
                "id": "the-verge",
                "name": "The Verge"
            },
            "author": "Jay Peters",
            "title": "Star Wars is getting a turn-based strategy game called Zero Company",
            "description": "The Star Wars strategy game announced in 2022 finally has a name: Zero Company, as EA revealed today. A website about the game describes it as a “single-player turn-based tactics game,” includes an image, and says that a “first look” will be shown at Star War…",
            "url": "https://www.theverge.com/news/648151/star-wars-zero-company-strategy-game-celebration",
            "urlToImage": "https://platform.theverge.com/wp-content/uploads/sites/2/2025/04/swzc-key-art.jpg.adapt_.1456w.jpg?quality=90&strip=all&crop=0%2C8.673903176521%2C88.8%2C82.652193646958&w=1200",
            "publishedAt": "2025-04-14T16:57:14Z",
            "content": "The Star Wars strategy game announced in 2022 finally has a name: Zero Company, as EA revealed today. A website about the game describes it as a “single-player turn-based tactics game,” includes an i… [+1068 chars]"
        },
        {
            "source": {
                "id": "the-verge",
                "name": "The Verge"
            },
            "author": "Jay Peters",
            "title": "Nintendo’s Switch 2 era comes at a price",
            "description": "Just about everything with the Nintendo Switch 2 is more expensive than the original Switch.  Itâs perhaps not unexpected that the console itself costs more money than the first Switch. That device launched more than eight years ago, after all. But followin…",
            "url": "https://www.theverge.com/games/642868/nintendo-switch-2-price-console-games-accessories",
            "urlToImage": "https://platform.theverge.com/wp-content/uploads/sites/2/2025/04/257672_switch_2_OGrove_0004.jpg?quality=90&strip=all&crop=0%2C10.805700988947%2C100%2C78.388598022106&w=1200",
            "publishedAt": "2025-04-03T17:59:01Z",
            "content": "From the console to the games to the accessories, things are more expensive.\r\nFrom the console to the games to the accessories, things are more expensive.\r\nJust about everything with the Nintendo Swi… [+2281 chars]"
        },
        {
            "source": {
                "id": "the-verge",
                "name": "The Verge"
            },
            "author": "Tom Hawking",
            "title": "22 years later, modders are keeping SimCity 4 alive",
            "description": "Search for âSimCity 4â on YouTube, and youâll see players constructing multilevel highway interchanges and intricate railroad networks, or maybe even a swooping flyby of a sprawling metropolis. None of these features came with the original game, which w…",
            "url": "https://www.theverge.com/tech/640021/simcity-4-mods",
            "urlToImage": "https://platform.theverge.com/wp-content/uploads/sites/2/2025/04/257578_Small_biz_CVirginia_SIMCITY-4.jpg?quality=90&strip=all&crop=0%2C10.732984293194%2C100%2C78.534031413613&w=1200",
            "publishedAt": "2025-04-04T16:39:03Z",
            "content": "The community continues to evolve the game.\r\nThe community continues to evolve the game.\r\nSearch for SimCity 4 on YouTube, and youll see players constructing multilevel highway interchanges and intri… [+8580 chars]"
        },
        {
            "source": {
                "id": "the-verge",
                "name": "The Verge"
            },
            "author": "Lewis Gordon",
            "title": "Skin Deep makes immersive sims messy and manic",
            "description": "Squidge, splodge, splat: Skin Deep doesn't sound like most immersive sims. It doesn't sound like most video games. Close your eyes and what it aurally resembles is a slapstick cartoon with a healthy dollop of toilet humor. These sounds, though, bookend chains…",
            "url": "https://www.theverge.com/games-review/656336/skin-deep-review-steam",
            "urlToImage": "https://platform.theverge.com/wp-content/uploads/sites/2/2025/04/ss_75aae5637edd506f5ff55fca747d5904573491a2.jpg?quality=90&strip=all&crop=0%2C3.4613147178592%2C100%2C93.077370564282&w=1200",
            "publishedAt": "2025-04-25T19:52:09Z",
            "content": "With sneeze mechanics and banana skins, the new game from Blendo plays like an action-cartoon fever dream.\r\nSquidge, splodge, splat: Skin Deep doesnt sound like most immersive sims. It doesnt sound l… [+5780 chars]"
        },
        {
            "source": {
                "id": "the-verge",
                "name": "The Verge"
            },
            "author": "Andrew Webster",
            "title": "The Last of Us ripped off the Band-aid",
            "description": "If youâve played both The Last of Us games and are watching along with the show, thereâs a pretty strong chance youâve been waiting to see how the HBO series approaches a very particular moment â and wondering if that moment has been changed at all fo…",
            "url": "https://www.theverge.com/tv/651902/the-last-of-us-season-2-joel",
            "urlToImage": "https://platform.theverge.com/wp-content/uploads/sites/2/2025/04/pedro-pascal_0.jpg?quality=90&strip=all&crop=0%2C10.732984293194%2C100%2C78.534031413613&w=1200",
            "publishedAt": "2025-04-21T12:31:28Z",
            "content": "If youve played both The Last of Us games and are watching along with the show, theres a pretty strong chance youve been waiting to see how the HBO series approaches a very particular moment and wond… [+3855 chars]"
        },
        {
            "source": {
                "id": "the-verge",
                "name": "The Verge"
            },
            "author": "Ash Parrish",
            "title": "Playing Oblivion for the first time is like opening an RPG time capsule",
            "description": "It was really great seeing all the excitement from fans when Oblivion shadow dropped earlier this week. For a lot of people, the fourth installment in the Elder Scrolls series is the game, the experience that either was the impetus for their career in video g…",
            "url": "https://www.theverge.com/games-review/654770/oblivion-remaster-hands-on-xbox-gamepass-bethesda",
            "urlToImage": "https://platform.theverge.com/wp-content/uploads/sites/2/2025/04/oblivion2.jpeg?quality=90&strip=all&crop=0%2C3.5340314136126%2C100%2C92.931937172775&w=1200",
            "publishedAt": "2025-04-23T20:34:19Z",
            "content": "Without the benefit of nostalgia, the remaster is a fascinating piece of history thats not very fun to play\r\nWithout the benefit of nostalgia, the remaster is a fascinating piece of history thats not… [+4805 chars]"
        },
        {
            "source": {
                "id": "the-verge",
                "name": "The Verge"
            },
            "author": "Jay Peters",
            "title": "Patreon will update its iPhone app to sidestep Apple’s payment system",
            "description": "Patreon is planning to submit an update to its iOS app that will let creators accept payments outside of Apple’s payment system, spokesperson Adiya Taylor tells The Verge. The planned update follows yesterday’s major Epic Games v. Apple ruling that blocks App…",
            "url": "https://www.theverge.com/news/659754/patreon-update-iphone-ios-app-apple-payment-system-ruling",
            "urlToImage": "https://platform.theverge.com/wp-content/uploads/sites/2/2025/05/STK326_PATREON_C.jpg?quality=90&strip=all&crop=0%2C10.732984293194%2C100%2C78.534031413613&w=1200",
            "publishedAt": "2025-05-01T19:32:15Z",
            "content": "The announcement follows a major court ruling blocking Apple from collecting fees on payments made outside of apps.\r\nThe announcement follows a major court ruling blocking Apple from collecting fees … [+1771 chars]"
        },
        {
            "source": {
                "id": "the-verge",
                "name": "The Verge"
            },
            "author": "Tom Warren",
            "title": "Microsoft’s Xbox app is now available on LG smart TVs",
            "description": "Microsoft revealed earlier this year that LG TVs would get access to Xbox Cloud Gaming, and now the Xbox TV app is rolling out to select LG smart TV models starting today. The Xbox app will let LG TV owners stream Xbox games directly to their TVs, and use a w…",
            "url": "https://www.theverge.com/news/654143/microsoft-xbox-app-lg-smart-tv-cloud-gaming-available-download",
            "urlToImage": "https://platform.theverge.com/wp-content/uploads/sites/2/2025/04/TIAX-LG-Hero-Shot-Trunk-1920x1080-1.png?quality=90&strip=all&crop=0%2C3.4613147178592%2C100%2C93.077370564282&w=1200",
            "publishedAt": "2025-04-23T11:49:46Z",
            "content": "LGs 2022 OLED TVs, select 2023 smart TVs, and other models can now download the Xbox app.\r\nLGs 2022 OLED TVs, select 2023 smart TVs, and other models can now download the Xbox app.\r\nMicrosoft reveale… [+1347 chars]"
        },
        {
            "source": {
                "id": "the-verge",
                "name": "The Verge"
            },
            "author": "Ash Parrish",
            "title": "Donkey Kong Bananza was best in show at the Switch 2 hands-on",
            "description": "One of the games I had on my personal Nintendo Switch 2 bingo card was a new 3D Mario. We didnât get one at the Switch 2 hands-on, and at first I thought it was odd that Nintendo would be launching their next big thing without a dedicated title for their nu…",
            "url": "https://www.theverge.com/games/642699/donkey-kong-bananza-hands-on-preview-switch-2",
            "urlToImage": "https://platform.theverge.com/wp-content/uploads/sites/2/2025/04/NintendoSwitch2_DonkeyKongBananza_SCRN_06-1.png?quality=90&strip=all&crop=0%2C3.4613147178592%2C100%2C93.077370564282&w=1200",
            "publishedAt": "2025-04-03T15:54:14Z",
            "content": "One of the games I had on my personal Nintendo Switch 2 bingo card was a new 3D Mario. We didnt get one at the Switch 2 hands-on, and at first I thought it was odd that Nintendo would be launching th… [+2006 chars]"
        },
        {
            "source": {
                "id": "the-verge",
                "name": "The Verge"
            },
            "author": "Sheena Vasani",
            "title": "Apple’s latest AirPods Pro are down to their best price of the year",
            "description": "Amazon’s annual Gaming Week sale might be the big focus this week as far as deals are concerned, but gaming peripherals and games aren’t the only discounts we’re seeing. Right now, for instance, Apple’s latest AirPods Pro with USB-C are on sale for $169 ($80 …",
            "url": "https://www.theverge.com/tech/639837/apple-airpods-pro-2-usb-c-wireless-earbuds-deal-sale",
            "urlToImage": "https://platform.theverge.com/wp-content/uploads/sites/2/2025/04/AirPods-Pro-USB-C-Deal-Image.png?quality=90&strip=all&crop=0%2C10.732984293194%2C100%2C78.534031413613&w=1200",
            "publishedAt": "2025-04-29T18:25:18Z",
            "content": "Apples premium earbuds remain the go-to pick for iPhone users who want the latest and greatest software features.\r\nApples premium earbuds remain the go-to pick for iPhone users who want the latest an… [+1527 chars]"
        },
        {
            "source": {
                "id": "the-verge",
                "name": "The Verge"
            },
            "author": "Jay Peters",
            "title": "Spotify already has an app ready to test Apple’s new rules",
            "description": "Spotify says it has submitted an update to its iOS app that would, among other things, let US customers use payment options that aren’t Apple’s, according to a blog post. The update submission follows Wednesday’s major Epic Games v. Apple ruling that forces A…",
            "url": "https://www.theverge.com/news/659891/spotify-ios-app-update-apple-payment-rules",
            "urlToImage": "https://platform.theverge.com/wp-content/uploads/sites/2/2025/01/KtzRDIOEJYs3A6mb9MaNfOeEAekXQwD5Omr7BQZWkzg.jpg?quality=90&strip=all&crop=0%2C10.732984293194%2C100%2C78.534031413613&w=1200",
            "publishedAt": "2025-05-01T22:04:15Z",
            "content": "The streaming company has already submitted an update to its iOS app following the major ruling in Epic Games v. Apple.\r\nThe streaming company has already submitted an update to its iOS app following… [+1999 chars]"
        },
        {
            "source": {
                "id": "the-verge",
                "name": "The Verge"
            },
            "author": "Dominic Preston",
            "title": "Apple approves Spotify app update with external payments",
            "description": "Apple has approved an update to Spotify’s iPhone app that makes it the first major app to support direct links for US users to pay for plans on an external site, without restrictions. Apple has been forced to change its rules on external payments following an…",
            "url": "https://www.theverge.com/news/660084/spotify-app-iphone-apple-update-external-payment-links",
            "urlToImage": "https://platform.theverge.com/wp-content/uploads/sites/2/chorus/uploads/chorus_asset/file/25378905/STK088_SPOTIFY_CVIRGINIA_A.jpg?quality=90&strip=all&crop=0%2C10.732984293194%2C100%2C78.534031413613&w=1200",
            "publishedAt": "2025-05-02T12:11:20Z",
            "content": "Following the update, Spotify can freely advertise prices to US users if they subscribe outside the app.\r\nFollowing the update, Spotify can freely advertise prices to US users if they subscribe outsi… [+1054 chars]"
        },
        {
            "source": {
                "id": "the-verge",
                "name": "The Verge"
            },
            "author": "Jay Peters",
            "title": "The Switch 2’s GameCube controller costs $64.99",
            "description": "Nintendo’s GameCube controller for the Switch 2 will cost $64.99, according to the controller’s listing on the company’s website. The controller releases on June 5th, the same day as the Switch 2, but Nintendo will be making it available to order ahead of tha…",
            "url": "https://www.theverge.com/news/655895/nintendo-switch-2-gamecube-controller-cost-online",
            "urlToImage": "https://platform.theverge.com/wp-content/uploads/sites/2/2025/04/257716_Switch_2_gamecube_CVirginia.jpg?quality=90&strip=all&crop=0%2C10.732984293194%2C100%2C78.534031413613&w=1200",
            "publishedAt": "2025-04-24T19:23:15Z",
            "content": "Might be worth the cost for the nostalgia.\r\nMight be worth the cost for the nostalgia.\r\nNintendos GameCube controller for the Switch 2 will cost $64.99, according to the controllers listing on the co… [+1181 chars]"
        },
        {
            "source": {
                "id": "the-verge",
                "name": "The Verge"
            },
            "author": "Andrew Webster",
            "title": "Remedy’s multiplayer Control spinoff FBC: Firebreak launches in June",
            "description": "The summer of video game releases is starting to heat up. Remedy Entertainment, the studio behind Alan Wake and Control, announced that its first multiplayer title FBC: Firebreak will launch on June 17th. It’ll be available on PC (both Steam and the Epic Game…",
            "url": "https://www.theverge.com/news/654718/fbc-firebreak-release-date-remedy-control",
            "urlToImage": "https://platform.theverge.com/wp-content/uploads/sites/2/2025/04/ss_eb0ca4c8db644f11a28cc76d351c95c10f8b4a4c.jpg?quality=90&strip=all&crop=0%2C3.4613147178592%2C100%2C93.077370564282&w=1200",
            "publishedAt": "2025-04-23T19:42:07Z",
            "content": "The supernatural universe gets a little bigger (and weirder).\r\nThe supernatural universe gets a little bigger (and weirder).\r\nThe summer of video game releases is starting to heat up. Remedy Entertai… [+1752 chars]"
        },
        {
            "source": {
                "id": "the-verge",
                "name": "The Verge"
            },
            "author": "Jay Peters",
            "title": "Vampire Survivors will let you share saves across platforms — but not on PlayStation",
            "description": "Vampire Survivors is finally launching cross-saves today, but they won’t be available on PlayStation to start and have a “very slim” chance of coming to the platform because of a “legal issue.”  “Last month, we told everyone that cross-save would be available…",
            "url": "https://www.theverge.com/news/646760/vampire-survivors-cross-saves-playstation-emerald-diorama",
            "urlToImage": "https://platform.theverge.com/wp-content/uploads/sites/2/2025/04/ss_6b951f8707c5d3b6b477ec7ce626a5e4554a37f5.jpg?quality=90&strip=all&crop=0%2C3.4613147178592%2C100%2C93.077370564282&w=1200",
            "publishedAt": "2025-04-10T19:02:34Z",
            "content": "The games developer says it ran into a legal issue.\r\nThe games developer says it ran into a legal issue.\r\nVampire Survivors is finally launching cross-saves today, but they wont be available on PlayS… [+1444 chars]"
        },
        {
            "source": {
                "id": "the-verge",
                "name": "The Verge"
            },
            "author": "Tom Warren",
            "title": "A first look at Microsoft’s new Xbox Copilot",
            "description": "Microsoft has started testing an early version of its Copilot for Gaming experience. Sources familiar with Microsoftâs Xbox plans tell me that employees can now access Copilot within the Xbox mobile app, and that while it looks similar to the existing Copil…",
            "url": "https://www.theverge.com/notepad-microsoft-newsletter/649665/microsoft-xbox-copilot-first-look-notepad",
            "urlToImage": "https://platform.theverge.com/wp-content/uploads/sites/2/2025/04/257700_Xbox_copilot_CVirginia.jpg?quality=90&strip=all&crop=0%2C10.732984293194%2C100%2C78.534031413613&w=1200",
            "publishedAt": "2025-04-16T14:13:10Z",
            "content": "Microsoft has started testing its new Copilot for Gaming experience with employees.\r\nMicrosoft has started testing its new Copilot for Gaming experience with employees.\r\nMicrosoft has started testing… [+8958 chars]"
        },
        {
            "source": {
                "id": "the-verge",
                "name": "The Verge"
            },
            "author": "Cameron Faulkner",
            "title": "How the Nintendo Switch 2 stacks up to the Steam Deck",
            "description": "The biggest threat to the Steam Deck in 2025 wonât be the arrival of other Windows-based handheld gaming PCs. Instead, itâll likely be the Nintendo Switch 2, which arrives on June 5 for $449.99 â smack dab between the cost of the $399 Steam Deck LCD and…",
            "url": "https://www.theverge.com/tech/642866/nintendo-switch-2-steam-deck-lcd-oled-comparison-specs-price",
            "urlToImage": "https://platform.theverge.com/wp-content/uploads/sites/2/2025/04/257673_Steam_deck_Switch_2_CVirginia.jpg?quality=90&strip=all&crop=0%2C10.732984293194%2C100%2C78.534031413613&w=1200",
            "publishedAt": "2025-04-03T20:07:36Z",
            "content": "They operate on different philosophies, yet theres overlap in their target audiences.\r\nThey operate on different philosophies, yet theres overlap in their target audiences.\r\nThe biggest threat to the… [+13139 chars]"
        },
        {
            "source": {
                "id": "the-verge",
                "name": "The Verge"
            },
            "author": "Ash Parrish",
            "title": "GTA V is Twitch’s most watched game of 2024",
            "description": "11 years after its launch, Grand Theft Auto V is still massively popular, becoming the most watched game on Twitch. The streaming platform has shared some of its viewership stats from last year with GTA V capturing over 1 billion hours watched. Here’s an info…",
            "url": "https://www.theverge.com/news/655394/gta-5-most-watched-twitch-game-gta-vi",
            "urlToImage": "https://platform.theverge.com/wp-content/uploads/sites/2/chorus/uploads/chorus_asset/file/25067501/480877775.jpg?quality=90&strip=all&crop=0%2C10.664146549656%2C100%2C78.671706900689&w=1200",
            "publishedAt": "2025-04-24T13:54:29Z",
            "content": "The game earned over 1 billion hours watched.\r\nThe game earned over 1 billion hours watched.\r\n11 years after its launch, Grand Theft Auto V is still massively popular, becoming the most watched game … [+1277 chars]"
        },
        {
            "source": {
                "id": "the-verge",
                "name": "The Verge"
            },
            "author": "Cameron Faulkner",
            "title": "The Meta Quest 3S just got its first discount",
            "description": "Due to the fluctuating tariff situation, a lot of people are seriously mulling over tech purchases they might otherwise be content to put off for a while. And it makes sense. While I don’t endorse panic buying, your reasons for buying now are more justified b…",
            "url": "https://www.theverge.com/tech/647954/meta-quest-3s-ps5-sale-deals",
            "urlToImage": "https://platform.theverge.com/wp-content/uploads/sites/2/chorus/uploads/chorus_asset/file/25639432/247283_Quest_3S_VPavic_0059.jpg?quality=90&strip=all&crop=0%2C10.732984293194%2C100%2C78.534031413613&w=1200",
            "publishedAt": "2025-04-14T14:36:35Z",
            "content": "As tech prices fluctuate, its refreshing to see some hardware deals.\r\nAs tech prices fluctuate, its refreshing to see some hardware deals.\r\nDue to the fluctuating tariff situation, a lot of people ar… [+2554 chars]"
        },
        {
            "source": {
                "id": "the-verge",
                "name": "The Verge"
            },
            "author": "Jay Peters",
            "title": "Duolingo is getting a chess course",
            "description": "Duolingo will soon be able to help you learn another new skill: chess. The platform’s new chess course will use short puzzles, such as moving a knight to the correct spot to practice its L-shaped movement or checkmating a king that’s stuck in a corner, to hel…",
            "url": "https://www.theverge.com/news/649319/duolingo-chess-course-ios-test",
            "urlToImage": "https://platform.theverge.com/wp-content/uploads/sites/2/2025/04/STKB350_DUOLINGO_B.jpg?quality=90&strip=all&crop=0%2C10.732984293194%2C100%2C78.534031413613&w=1200",
            "publishedAt": "2025-04-17T22:44:54Z",
            "content": "Practice the classic game with help from Duolingo.\r\nPractice the classic game with help from Duolingo.\r\nDuolingo will soon be able to help you learn another new skill: chess.\r\nThe platforms new chess… [+1351 chars]"
        },
        {
            "source": {
                "id": "the-verge",
                "name": "The Verge"
            },
            "author": "Sean Hollister",
            "title": "Game Boy clone maker Anbernic suspends all shipments to US",
            "description": "How much will Trump’s threatened 245 percent tariffs truly impact Chinese goods and the prices we pay in the US? Some Chinese companies aren’t waiting to see. Anbernic, which makes excellent and controversial Nintendo Game Boy clones, is already suspending US…",
            "url": "https://www.theverge.com/news/652797/anbernic-suspend-shipments-tariffs-us-china",
            "urlToImage": "https://platform.theverge.com/wp-content/uploads/sites/2/chorus/uploads/chorus_asset/file/25781281/anbernic_gba_date.jpg?quality=90&strip=all&crop=0%2C10.708834837039%2C100%2C78.582330325921&w=1200",
            "publishedAt": "2025-04-21T20:15:14Z",
            "content": "How much will Trump’s threatened 245 percent tariffs truly impact Chinese goods and the prices we pay in the US? Some Chinese companies aren’t waiting to see. Anbernic, which makes excellent and cont… [+3170 chars]"
        },
        {
            "source": {
                "id": "the-verge",
                "name": "The Verge"
            },
            "author": "Tom Warren",
            "title": "Nvidia’s RTX 5060 Ti arrives on April 16th starting at $379",
            "description": "Nvidia is announcing its RTX 5060 family of GPUs today, just a day before it releases the RTX 5060 Ti on April 16th. Two variants of the RTX 5060 Ti are launching, the $379 8GB of VRAM model and the $429 16GB version. The $299 RTX 5060 will launch at some poi…",
            "url": "https://www.theverge.com/news/648705/nvidias-rtx-5060-ti-gpu-pricing-release-date",
            "urlToImage": "https://platform.theverge.com/wp-content/uploads/sites/2/2025/04/5060hed.png?quality=90&strip=all&crop=0%2C3.340661617056%2C100%2C93.318676765888&w=1200",
            "publishedAt": "2025-04-15T13:02:36Z",
            "content": "The $299 RTX 5060 is also releasing in May to give PC gamers more GPU options.\r\nThe $299 RTX 5060 is also releasing in May to give PC gamers more GPU options.\r\nNvidia is announcing its RTX 5060 famil… [+3153 chars]"
        },
        {
            "source": {
                "id": "the-verge",
                "name": "The Verge"
            },
            "author": "Andrew Webster",
            "title": "In The Last of Us season 2, Joel finally goes to therapy",
            "description": "Joel is a troubled guy. Throughout the first Last of Us game (and subsequent TV adaptation on HBO, where heâs played by Pedro Pascal), he sees and does a lot of things heâd rather forget. He certainly doesnât seem to want to talk about them much. Which …",
            "url": "https://www.theverge.com/tv/647211/last-of-us-season-2-therapist-catherine-ohara",
            "urlToImage": "https://platform.theverge.com/wp-content/uploads/sites/2/2025/04/pedro-pascal-catherine-o-hara.jpg?quality=90&strip=all&crop=0%2C10.732984293194%2C100%2C78.534031413613&w=1200",
            "publishedAt": "2025-04-11T18:26:32Z",
            "content": "The team behind the show explains a brand-new character played by Catherine OHara.\r\nThe team behind the show explains a brand-new character played by Catherine OHara.\r\nJoel is a troubled guy. Through… [+2557 chars]"
        },
        {
            "source": {
                "id": "the-verge",
                "name": "The Verge"
            },
            "author": "Richard Lawler",
            "title": "Nintendo’s new Switch 1 update is getting things ready for Switch 2",
            "description": "With just over a month to go before the Nintendo Switch 2 release date on June 5th, Nintendo has released a Switch 1 update that will help prepare things for the new console’s arrival. The V20.0.0 update for the original Switch adds a bunch of new features th…",
            "url": "https://www.theverge.com/news/658511/nintendo-switch-20-0-0-update-virtual-game-card-gameshare-switch-2",
            "urlToImage": "https://platform.theverge.com/wp-content/uploads/sites/2/chorus/uploads/chorus_asset/file/19086557/akrales_190820_3597_0105.jpg?quality=90&strip=all&crop=0%2C13.730687382304%2C100%2C78.534031413613&w=1200",
            "publishedAt": "2025-04-30T02:34:15Z",
            "content": "This update gets your Switch 1 ready for a system transfer to Switch 2, as well as GameShare and Virtual Game Cards.\r\nThis update gets your Switch 1 ready for a system transfer to Switch 2, as well a… [+2960 chars]"
        }
    ]
}